{
  "settings": {
    "theme": "warm"
  },
  "todolists": [
    {
      "listId": "62a85f04-f613-4e76-949a-525dfd10f034",
      "creationDate": "2024-11-05T13:57:32.160Z",
      "title": "План по созданию новогоднего настроения",
      "items": [
        {
          "id": "951b7027-b2fb-4f8f-b055-20abca685e40",
          "title": "Украсить дом гирляндами и огоньками",
          "isDone": false
        },
        {
          "id": "026b8f36-74fc-4e14-a335-fc18d05c7fee",
          "title": "Составить новогодний плейлист",
          "isDone": false
        },
        {
          "id": "d67e287f-58bf-4d04-be7a-be01a53223c3",
          "title": "Устроить марафон по просмотру картин с духом праздника",
          "isDone": false
        },
        {
          "id": "3419cc97-2beb-40ff-b797-115f6cf624ae",
          "title": "Купить ароматные мандарины",
          "isDone": false
        },
        {
          "id": "67c4e8d8-ee19-449e-b050-d4cb13d8756e",
          "title": "Попробовать испечь имбирное печенье",
          "isDone": false
        },
        {
          "id": "08dae184-aaf8-4359-aee7-fc8625b57b51",
          "title": "Купить и упаковать близким подарки",
          "isDone": false
        },
        {
          "id": "5f5e87d0-e87f-4a3f-a992-a200606c98cb",
          "title": "Купить новогодний свитер",
          "isDone": false
        },
        {
          "id": "4d785cb3-01d5-4351-9a1b-1fdd0c643426",
          "title": "Отправить близким новогодние открытки",
          "isDone": false
        },
        {
          "id": "5b860759-fd41-4a70-b375-8532293fecab",
          "title": "Нарядить елку",
          "isDone": false
        }
      ],
      "id": "62a85f04-f613-4e76-949a-525dfd10f034"
    },
    {
      "listId": "93caceba-8ac4-4513-ac89-e438a604756d",
      "creationDate": "2024-11-05T13:57:32.161Z",
      "title": "Поиск работы",
      "items": [
        {
          "id": "ced91316-47e5-48fd-81b8-bc006808b128",
          "title": "Проверить почту на наличие ответов от работодателей",
          "isDone": false
        },
        {
          "id": "8804e608-a7e3-45bd-8c00-0471cf0cf99e",
          "title": "Проверить сообщения в Telegram от рекрутеров",
          "isDone": false
        },
        {
          "id": "ad6cadda-11a5-40ea-b01a-608af7dab9ff",
          "title": "Проверить новые вакансии на HeadHunter и в других источниках",
          "isDone": true
        },
        {
          "id": "0c568f7e-5b69-4604-8c69-9b02d8e8ce52",
          "title": "Повторить теоретические вопросы для интервью",
          "isDone": true
        },
        {
          "id": "1c481559-b427-41f8-aac0-df20f481b2df",
          "title": "Практиковаться в решении алгоритмических задач",
          "isDone": true
        },
        {
          "id": "c6adab75-8331-4704-b87e-e514264793e8",
          "title": "Минимум один коммит в пет-проект для улучшения практических навыков",
          "isDone": false
        },
        {
          "id": "a7ef2757-42bb-4c40-977b-8cced5caecbd",
          "title": "Всё получится!",
          "isDone": false
        }
      ],
      "id": "93caceba-8ac4-4513-ac89-e438a604756d"
    },
    {
      "id": "e4bb5784-b5c2-484b-92d5-9360fe847cab",
      "creationDate": "2024-11-05T13:57:32.162Z",
      "title": "План уборки на выходных",
      "items": [
        {
          "id": "bbca07ef-d8b8-4cb9-9a6b-49a88d692945",
          "title": "Раковина на кухне",
          "isDone": false
        },
        {
          "id": "887cb827-d05b-4f35-ade9-81d9a175160c",
          "title": "Кухонная стойка",
          "isDone": false
        },
        {
          "id": "4a0b9949-9319-4835-882c-d82a2f4cc977",
          "title": "Плита и стены рядом",
          "isDone": false
        },
        {
          "id": "1848ab7e-08e3-4d53-8c86-e9bc26bf6ef3",
          "title": "Ванная комната",
          "isDone": false
        },
        {
          "id": "267219ec-4534-4862-be0d-c921774dfcb1",
          "title": "Туалет",
          "isDone": false
        },
        {
          "id": "aeb87a6d-21da-4c38-a527-056e12970431",
          "title": "Пропылесосить",
          "isDone": false
        },
        {
          "id": "4f63ae59-78b9-4b8d-a9ce-b2784f57d784",
          "title": "Вынести коробки",
          "isDone": false
        },
        {
          "id": "4095013b-1670-4d3d-bbd9-44d039623310",
          "title": "Помыть окна и зеркала",
          "isDone": false
        }
      ]
    }
  ]
}